polarishub_flask/__init__.py
polarishub_flask/app.py
polarishub_flask/files/about.html
polarishub_flask/server/__init__.py
polarishub_flask/server/file_handler.py
polarishub_flask/server/handler.py
polarishub_flask/server/help.py
polarishub_flask/server/myqrcode.py
polarishub_flask/server/network.py
polarishub_flask/server/parser.py
polarishub_flask/server/settings.json
polarishub_flask/server/__pycache__/__init__.cpython-36.pyc
polarishub_flask/server/__pycache__/file_handler.cpython-36.pyc
polarishub_flask/server/__pycache__/help.cpython-36.pyc
polarishub_flask/server/__pycache__/myqrcode.cpython-36.pyc
polarishub_flask/server/__pycache__/network.cpython-36.pyc
polarishub_flask/server/__pycache__/parser.cpython-36.pyc
polarishub_flask/server/static/about-cn.html
polarishub_flask/server/static/about.html
polarishub_flask/server/static/favicon.ico
polarishub_flask/server/static/hello_world.txt
polarishub_flask/server/static/help-cn.html
polarishub_flask/server/static/help.html
polarishub_flask/server/static/css/all.css
polarishub_flask/server/static/css/all.min.css
polarishub_flask/server/static/css/bootstrap-grid.css
polarishub_flask/server/static/css/bootstrap-grid.css.map
polarishub_flask/server/static/css/bootstrap-grid.min.css
polarishub_flask/server/static/css/bootstrap-grid.min.css.map
polarishub_flask/server/static/css/bootstrap-reboot.css
polarishub_flask/server/static/css/bootstrap-reboot.css.map
polarishub_flask/server/static/css/bootstrap-reboot.min.css
polarishub_flask/server/static/css/bootstrap-reboot.min.css.map
polarishub_flask/server/static/css/bootstrap.css
polarishub_flask/server/static/css/bootstrap.css.map
polarishub_flask/server/static/css/bootstrap.min.css
polarishub_flask/server/static/css/bootstrap.min.css.map
polarishub_flask/server/static/css/brands.css
polarishub_flask/server/static/css/brands.min.css
polarishub_flask/server/static/css/fontawesome.css
polarishub_flask/server/static/css/fontawesome.min.css
polarishub_flask-0.1.17.dist-info/LICENSE
polarishub_flask-0.1.17.dist-info/METADATA
polarishub_flask-0.1.17.dist-info/WHEEL
polarishub_flask-0.1.17.dist-info/entry_points.txt
polarishub_flask-0.1.17.dist-info/top_level.txt
polarishub_flask-0.1.17.dist-info/RECORD
