Metadata-Version: 2.1
Name: polarishub-flask
Version: 0.1.17
Summary: PolarisHub Flask version
Home-page: https://github.com/XieGuochao/polarishub_flask
Author: Guochao Xie & Senyue Hao
Author-email: guochaoxie@link.cuhk.edu.cn
License: UNKNOWN
Platform: UNKNOWN
Classifier: Programming Language :: Python :: 3
Classifier: License :: OSI Approved :: MIT License
Classifier: Operating System :: OS Independent
Requires-Dist: Flask
Requires-Dist: qrcode
Requires-Dist: Pillow
